uprock_sdk/__init__.py
uprock_sdk/customers.py
uprock_sdk/mass_messages.py
uprock_sdk/settings.py
uprock_sdk/telegram_bots.py
uprock_sdk/terms.py
uprock_sdk/types.py
uprock_sdk-0.1.49.dist-info/METADATA
uprock_sdk-0.1.49.dist-info/WHEEL
uprock_sdk-0.1.49.dist-info/RECORD
