Metadata-Version: 2.4
Name: uprock-sdk
Version: 0.1.49
Summary: 
Author: Aleksey Dalekin
Author-email: ald@approck.pro
Requires-Python: >=3.10,<4.0
Classifier: Programming Language :: Python :: 3
Classifier: Programming Language :: Python :: 3.10
Classifier: Programming Language :: Python :: 3.11
Classifier: Programming Language :: Python :: 3.12
Classifier: Programming Language :: Python :: 3.13
Classifier: Programming Language :: Python :: 3.14
Requires-Dist: html-sanitizer (>=2.4.2,<3.0.0)
Requires-Dist: httpx (>=0.27.0)
Requires-Dist: jinja2 (>=3.1.4,<4.0.0)
Requires-Dist: pydantic (>=2.7.1,<3.0.0)
Requires-Dist: pydantic-settings (>=2.2.1,<3.0.0)
Requires-Dist: typing-extensions (>=4.11.0,<5.0.0)
